[{"generic_name": "amlodipine and atorvastatin","contraindications": [{"contraindication_name": "pregnancy","contraindication_type": "physiological_condition","severity": "absolute","reason": "Atorvastatin is Pregnancy Category X; may cause fetal harm. Discontinue if pregnancy is detected."},{"contraindication_name": "breastfeeding","contraindication_type": "physiological_condition","severity": "relative","reason": "Atorvastatin may pass into breast milk, potential risk to the infant; avoid use or discontinue breastfeeding."},{"contraindication_name": "active liver disease or unexplained persistent transaminase elevation","contraindication_type": "disease","severity": "absolute","reason": "Atorvastatin is contraindicated due to hepatotoxicity risk."},{"contraindication_name": "severe hypotension","contraindication_type": "disease","severity": "absolute","reason": "Amlodipine can exacerbate hypotension."},{"contraindication_name": "cardiogenic shock","contraindication_type": "disease","severity": "absolute","reason": "Amlodipine further reduces cardiac output."},{"contraindication_name": "hypersensitivity to dihydropyridines or statins","contraindication_type": "allergy_type","severity": "absolute","reason": "Cross-allergy potential; anaphylaxis and angioedema can occur."},{"contraindication_name": "concomitant strong CYP3A4 inhibitors","contraindication_type": "drug_class","severity": "relative","reason": "Increased risk of myopathy/rhabdomyolysis with atorvastatin and elevated amlodipine levels."},{"contraindication_name": "severe aortic stenosis","contraindication_type": "disease","severity": "relative","reason": "Amlodipine may cause coronary steal or severe hypotension in critically obstructed outflow."},{"contraindication_name": "acute myocardial infarction","contraindication_type": "disease","severity": "relative","reason": "Amlodipine should be used cautiously in unstable coronary syndromes."},{"contraindication_name": "severe renal impairment (atorvastatin component)","contraindication_type": "disease","severity": "relative","reason": "No dose adjustment needed, but monitor for muscle toxicity."}]},{"generic_name": "nitroglycerin (oral route, sublingual route)","contraindications": [{"contraindication_name": "concomitant use of PDE5 inhibitors (e.g., sildenafil, tadalafil)","contraindication_type": "drug_class","severity": "absolute","reason": "Profound hypotension, cardiovascular collapse."},{"contraindication_name": "concomitant use of riociguat","contraindication_type": "drug_class","severity": "absolute","reason": "Severe hypotension."},{"contraindication_name": "severe anemia","contraindication_type": "disease","severity": "absolute","reason": "Nitrates can oxidize hemoglobin to methemoglobin, worsening oxygen delivery."},{"contraindication_name": "increased intracranial pressure, head trauma, cerebral hemorrhage","contraindication_type": "disease","severity": "absolute","reason": "Cerebral vasodilation raises intracranial pressure."},{"contraindication_name": "severe hypotension / systolic BP <90 mmHg","contraindication_type": "disease","severity": "absolute","reason": "Further vasodilation can cause cardiovascular collapse."},{"contraindication_name": "hypersensitivity to nitrates","contraindication_type": "allergy_type","severity": "absolute","reason": "Allergic reaction including contact dermatitis."},{"contraindication_name": "angle-closure glaucoma","contraindication_type": "disease","severity": "relative","reason": "May increase intraocular pressure."},{"contraindication_name": "hypertrophic obstructive cardiomyopathy","contraindication_type": "disease","severity": "relative","reason": "Decreased preload may worsen outflow obstruction."},{"contraindication_name": "pregnancy (Category C)","contraindication_type": "physiological_condition","severity": "relative","reason": "Use only if benefit outweighs risk; potential fetal harm."},{"contraindication_name": "hypovolemia","contraindication_type": "disease","severity": "relative","reason": "Decreased venous return may cause profound hypotension."}]},{"generic_name": "verapamil (oral/injection)","contraindications": [{"contraindication_name": "severe left ventricular dysfunction","contraindication_type": "disease","severity": "absolute","reason": "Negative inotropic effect worsens heart failure unless caused by rapid atrial fibrillation."},{"contraindication_name": "cardiogenic shock","contraindication_type": "disease","severity": "absolute","reason": "Further myocardial depression."},{"contraindication_name": "hypotension (systolic BP <90 mmHg)","contraindication_type": "disease","severity": "absolute","reason": "Vasodilation can cause cardiovascular collapse."},{"contraindication_name": "sick sinus syndrome (without pacemaker)","contraindication_type": "disease","severity": "absolute","reason": "Risk of severe bradycardia and asystole."},{"contraindication_name": "second- or third-degree AV block (without pacemaker)","contraindication_type": "disease","severity": "absolute","reason": "Conduction block can be exacerbated to complete heart block."},{"contraindication_name": "atrial flutter/fibrillation with accessory pathway (e.g., WPW)","contraindication_type": "disease","severity": "absolute","reason": "May increase ventricular response and degenerate to ventricular fibrillation."},{"contraindication_name": "hypersensitivity to verapamil","contraindication_type": "allergy_type","severity": "absolute","reason": "Anaphylaxis possible."},{"contraindication_name": "concomitant intravenous beta-blockers","contraindication_type": "drug_class","severity": "absolute","reason": "Additive negative inotropy, risk of bradycardia and asystole."},{"contraindication_name": "severe hepatic impairment","contraindication_type": "disease","severity": "relative","reason": "Verapamil extensively metabolized by liver; reduce dose."},{"contraindication_name": "pregnancy (Category C)","contraindication_type": "physiological_condition","severity": "relative","reason": "Only if clearly needed; may cause fetal bradycardia."},{"contraindication_name": "lactation","contraindication_type": "physiological_condition","severity": "relative","reason": "Excreted in breast milk; monitor infant for bradycardia."}]},{"generic_name": "Aspirin Enteric-Coated and Buffered Tablets","contraindications": [{"contraindication_name": "aspirin hypersensitivity or NSAID cross-allergy","contraindication_type": "allergy_type","severity": "absolute","reason": "Bronchospasm, anaphylaxis, aspirin-exacerbated respiratory disease (AERD)."},{"contraindication_name": "active peptic ulcer disease","contraindication_type": "disease","severity": "absolute","reason": "Gastrointestinal bleeding and perforation risk."},{"contraindication_name": "bleeding disorders (hemophilia, thrombocytopenia)","contraindication_type": "disease","severity": "absolute","reason": "Antiplatelet effect increases life-threatening bleeding."},{"contraindication_name": "children with viral infection (especially varicella, influenza)","contraindication_type": "physiological_condition","severity": "absolute","reason": "Reye syndrome risk."},{"contraindication_name": "third trimester of pregnancy","contraindication_type": "physiological_condition","severity": "absolute","reason": "Premature ductus arteriosus closure, prolonged labor, fetal and maternal bleeding."},{"contraindication_name": "severe renal impairment","contraindication_type": "disease","severity": "relative","reason": "Risk of renal failure, sodium and water retention."},{"contraindication_name": "severe hepatic impairment","contraindication_type": "disease","severity": "relative","reason": "Altered metabolism, increased bleeding risk."},{"contraindication_name": "concomitant anticoagulants (warfarin, heparin, DOACs)","contraindication_type": "drug_class","severity": "relative","reason": "Synergistic bleeding risk."},{"contraindication_name": "lactation","contraindication_type": "physiological_condition","severity": "relative","reason": "Enters breast milk; risk of Reye syndrome and bleeding in infant."}]},{"generic_name": "amlodipine (oral route)","contraindications": [{"contraindication_name": "hypersensitivity to dihydropyridines","contraindication_type": "allergy_type","severity": "absolute","reason": "Allergic reactions including angioedema."},{"contraindication_name": "severe hypotension","contraindication_type": "disease","severity": "absolute","reason": "Further vasodilation can cause collapse."},{"contraindication_name": "cardiogenic shock","contraindication_type": "disease","severity": "absolute","reason": "Can further reduce cardiac output."},{"contraindication_name": "severe aortic stenosis","contraindication_type": "disease","severity": "relative","reason": "Risk of coronary hypoperfusion and severe hypotension."},{"contraindication_name": "unstable angina","contraindication_type": "disease","severity": "relative","reason": "Reflex tachycardia may aggravate ischemia; use with caution."},{"contraindication_name": "severe hepatic impairment","contraindication_type": "disease","severity": "relative","reason": "Reduced clearance; titrate slowly and reduce dose."},{"contraindication_name": "pregnancy (Category C)","contraindication_type": "physiological_condition","severity": "relative","reason": "Use only if benefit outweighs risk."},{"contraindication_name": "coprescription with strong CYP3A4 inhibitors","contraindication_type": "drug_class","severity": "relative","reason": "Increased amlodipine exposure, hypotension."}]},{"generic_name": "Aspirin Tablets","contraindications": [{"contraindication_name": "aspirin hypersensitivity or NSAID cross-allergy","contraindication_type": "allergy_type","severity": "absolute","reason": "Bronchospasm, anaphylaxis, AERD."},{"contraindication_name": "active peptic ulcer disease","contraindication_type": "disease","severity": "absolute","reason": "Gastrointestinal bleeding and perforation."},{"contraindication_name": "bleeding disorders","contraindication_type": "disease","severity": "absolute","reason": "Antiplatelet effect increases bleeding."},{"contraindication_name": "children with viral infections","contraindication_type": "physiological_condition","severity": "absolute","reason": "Reye syndrome."},{"contraindication_name": "third trimester pregnancy","contraindication_type": "physiological_condition","severity": "absolute","reason": "Premature ductus closure, maternal/fetal hemorrhage."},{"contraindication_name": "severe renal impairment","contraindication_type": "disease","severity": "relative","reason": "Risk of renal failure."},{"contraindication_name": "severe hepatic impairment","contraindication_type": "disease","severity": "relative","reason": "Altered metabolism, bleeding risk."},{"contraindication_name": "concomitant anticoagulants","contraindication_type": "drug_class","severity": "relative","reason": "Additive bleeding risk."}]},{"generic_name": "nitroglycerin (transdermal)","contraindications": [{"contraindication_name": "concomitant PDE5 inhibitors","contraindication_type": "drug_class","severity": "absolute","reason": "Profound hypotension."},{"contraindication_name": "concomitant riociguat","contraindication_type": "drug_class","severity": "absolute","reason": "Severe hypotension."},{"contraindication_name": "severe anemia","contraindication_type": "disease","severity": "absolute","reason": "Methemoglobinemia risk."},{"contraindication_name": "increased intracranial pressure/cerebral hemorrhage","contraindication_type": "disease","severity": "absolute","reason": "Further elevation of ICP."},{"contraindication_name": "severe hypotension (SBP <90 mmHg)","contraindication_type": "disease","severity": "absolute","reason": "Vasodilation may cause collapse."},{"contraindication_name": "hypersensitivity to nitrates or patch adhesive","contraindication_type": "allergy_type","severity": "absolute","reason": "Contact dermatitis or anaphylaxis."},{"contraindication_name": "angle-closure glaucoma","contraindication_type": "disease","severity": "relative","reason": "May increase intraocular pressure."},{"contraindication_name": "hypertrophic obstructive cardiomyopathy","contraindication_type": "disease","severity": "relative","reason": "Worsening outflow obstruction."},{"contraindication_name": "pregnancy (Category C)","contraindication_type": "physiological_condition","severity": "relative","reason": "Risk-benefit assessment required."}]},{"generic_name": "heparin (injection)","contraindications": [{"contraindication_name": "active major bleeding","contraindication_type": "disease","severity": "absolute","reason": "Life-threatening hemorrhage."},{"contraindication_name": "history of heparin-induced thrombocytopenia (HIT)","contraindication_type": "disease","severity": "absolute","reason": "Risk of HIT Type II with thrombosis."},{"contraindication_name": "hypersensitivity to heparin or pork products","contraindication_type": "allergy_type","severity": "absolute","reason": "Allergic reactions including anaphylaxis."},{"contraindication_name": "severe thrombocytopenia","contraindication_type": "disease","severity": "absolute","reason": "Increased bleeding risk."},{"contraindication_name": "recentcentral nervous system surgery or hemorrhage","contraindication_type": "disease","severity": "absolute","reason": "Risk of catastrophic intracranial bleeding."},{"contraindication_name": "severe hypertension (uncontrolled)","contraindication_type": "disease","severity": "relative","reason": "Hemorrhagic stroke risk."},{"contraindication_name": "bacterial endocarditis","contraindication_type": "disease","severity": "relative","reason": "Risk of cerebral hemorrhage from septic emboli."},{"contraindication_name": "severe liver disease with esophageal varices","contraindication_type": "disease","severity": "relative","reason": "Hemorrhage risk."},{"contraindication_name": "concomitant antiplatelets, thrombolytics, or anticoagulants","contraindication_type": "drug_class","severity": "relative","reason": "Additive bleeding risk."},{"contraindication_name": "lumbar puncture or regional anesthesia","contraindication_type": "disease","severity": "relative","reason": "Spinal/epidural hematoma."}]},{"generic_name": "propranolol (oral route)","contraindications": [{"contraindication_name": "bronchial asthma or severe COPD","contraindication_type": "disease","severity": "absolute","reason": "Non-selective beta-blockade can induce life-threatening bronchospasm."},{"contraindication_name": "cardiogenic shock","contraindication_type": "disease","severity": "absolute","reason": "Further myocardial depression."},{"contraindication_name": "decompensated heart failure","contraindication_type": "disease","severity": "absolute","reason": "Negative inotropy exacerbates failure."},{"contraindication_name": "sick sinus syndrome","contraindication_type": "disease","severity": "absolute","reason": "Severe bradycardia, asystole."},{"contraindication_name": "second- or third-degree AV block (no pacemaker)","contraindication_type": "disease","severity": "absolute","reason": "Exacerbation to complete heart block."},{"contraindication_name": "hypersensitivity to propranolol or beta-blockers","contraindication_type": "allergy_type","severity": "absolute","reason": "Anaphylaxis."},{"contraindication_name": "severe peripheral arterial disease","contraindication_type": "disease","severity": "relative","reason": "May precipitate critical limb ischemia."},{"contraindication_name": "Prinzmetal variant angina","contraindication_type": "disease","severity": "relative","reason": "Unstable coronary vasospasm; beta-blockade may worsen."},{"contraindication_name": "untreated pheochromocytoma","contraindication_type": "disease","severity": "relative","reason": "Paradoxical hypertension; must initiate alpha-blockade first."},{"contraindication_name": "pregnancy (Category C)","contraindication_type": "physiological_condition","severity": "relative","reason": "Fetal/neonatal bradycardia, hypoglycemia; use only if clearly needed."},{"contraindication_name": "concomitant with verapamil or diltiazem","contraindication_type": "drug_class","severity": "relative","reason": "Additive negative inotropy and bradycardia."}]},{"generic_name": "Metoprolol Extended-Release Capsules","contraindications": [{"contraindication_name": "severe bradycardia","contraindication_type": "disease","severity": "absolute","reason": "Heart rate <45 bpm at rest, risk of asystole."},{"contraindication_name": "cardiogenic shock","contraindication_type": "disease","severity": "absolute","reason": "Further reducing cardiac output."},{"contraindication_name": "decompensated heart failure","contraindication_type": "disease","severity": "absolute","reason": "Inotropic depression worsens fluid retention and hypotension."},{"contraindication_name": "sick sinus syndrome","contraindication_type": "disease","severity": "absolute","reason": "Bradycardia and sinus arrest."},{"contraindication_name": "second- or third-degree AV block (no pacemaker)","contraindication_type": "disease","severity": "absolute","reason": "May cause complete heart block."},{"contraindication_name": "hypersensitivity to metoprolol or beta-blockers","contraindication_type": "allergy_type","severity": "absolute","reason": "Anaphylaxis risk."},{"contraindication_name": "bronchospastic lung disease","contraindication_type": "disease","severity": "relative","reason": "Cardioselective beta-1 antagonist but still can provoke bronchospasm; use caution."},{"contraindication_name": "severe peripheral arterial disease","contraindication_type": "disease","severity": "relative","reason": "Possible precipitation of claudication or gangrene."},{"contraindication_name": "untreated pheochromocytoma","contraindication_type": "disease","severity": "relative","reason": "Hypertensive crisis without alpha blockade."},{"contraindication_name": "pregnancy (Category C)","contraindication_type": "physiological_condition","severity": "relative","reason": "May cause fetal bradycardia, neonatal hypoglycemia; use if benefit justifies."},{"contraindication_name": "lactation","contraindication_type": "physiological_condition","severity": "relative","reason": "Concentrated in breast milk; infant may develop bradycardia."},{"contraindication_name": "concomitant verapamil or diltiazem","contraindication_type": "drug_class","severity": "relative","reason": "Additive cardiodepression."}]},{"generic_name": "nitroglycerin (topical)","contraindications": [{"contraindication_name": "concomitant PDE5 inhibitors","contraindication_type": "drug_class","severity": "absolute","reason": "Profound hypotension."},{"contraindication_name": "concomitant riociguat","contraindication_type": "drug_class","severity": "absolute","reason": "Severe hypotension."},{"contraindication_name": "severe anemia","contraindication_type": "disease","severity": "absolute","reason": "Methemoglobinemia risk."},{"contraindication_name": "increased intracranial pressure/cerebral hemorrhage","contraindication_type": "disease","severity": "absolute","reason": "Intracranial pressure elevation."},{"contraindication_name": "severe hypotension (SBP <90 mmHg)","contraindication_type": "disease","severity": "absolute","reason": "Vasodilation can cause collapse."},{"contraindication_name": "hypersensitivity to nitrates or ointment base","contraindication_type": "allergy_type","severity": "absolute","reason": "Contact dermatitis, anaphylaxis."},{"contraindication_name": "angle-closure glaucoma","contraindication_type": "disease","severity": "relative","reason": "Possible increased intraocular pressure."},{"contraindication_name": "local skin damage at application site","contraindication_type": "disease","severity": "relative","reason": "Enhanced systemic absorption, inconsistent dosing."},{"contraindication_name": "pregnancy (Category C)","contraindication_type": "physiological_condition","severity": "relative","reason": "Only if benefit outweighs risk."}]},{"generic_name": "dalteparin","contraindications": [{"contraindication_name": "active major bleeding","contraindication_type": "disease","severity": "absolute","reason": "Life-threatening hemorrhage."},{"contraindication_name": "history of heparin-induced thrombocytopenia (HIT)","contraindication_type": "disease","severity": "absolute","reason": "Risk of HIT Type II with thrombosis; may cross-react with LMWH."},{"contraindication_name": "hypersensitivity to dalteparin, heparin, or pork products","contraindication_type": "allergy_type","severity": "absolute","reason": "Anaphylaxis, allergic reactions."},{"contraindication_name": "recent neuraxial anesthesia or spinal puncture","contraindication_type": "disease","severity": "absolute","reason": "Spinal/epidural hematoma causing paralysis."},{"contraindication_name": "severe coagulation disorders","contraindication_type": "disease","severity": "relative","reason": "Uncontrolled bleeding risk."},{"contraindication_name": "severe uncontrolled hypertension","contraindication_type": "disease","severity": "relative","reason": "Intracranial hemorrhage risk."},{"contraindication_name": "severe hepatic impairment","contraindication_type": "disease","severity": "relative","reason": "Coagulopathy may amplify bleeding."},{"contraindication_name": "severe renal impairment (CrCl <30 mL/min)","contraindication_type": "disease","severity": "relative","reason": "Accumulation and increased bleeding; dose adjustment or switch to heparin required."},{"contraindication_name": "concomitant antiplatelets, NSAIDs, other anticoagulants","contraindication_type": "drug_class","severity": "relative","reason": "Additive bleeding risk."}]},{"generic_name": "bivalirudin","contraindications": [{"contraindication_name": "active major bleeding","contraindication_type": "disease","severity": "absolute","reason": "Direct thrombin inhibition exacerbates hemorrhage."},{"contraindication_name": "hypersensitivity to bivalirudin or components","contraindication_type": "allergy_type","severity": "absolute","reason": "Anaphylaxis reported."},{"contraindication_name": "recent major surgery or trauma","contraindication_type": "disease","severity": "relative","reason": "High bleeding risk."},{"contraindication_name": "intracranial aneurysm or recent cerebral hemorrhage","contraindication_type": "disease","severity": "relative","reason": "Catastrophic intracranial bleeding."},{"contraindication_name": "severe uncontrolled hypertension","contraindication_type": "disease","severity": "relative","reason": "Hemorrhagic stroke."},{"contraindication_name": "severe renal impairment (CrCl <30 mL/min)","contraindication_type": "disease","severity": "relative","reason": "Reduced clearance; dose reduction imperative, with increased bleeding risk."},{"contraindication_name": "concomitant antiplatelets, thrombolytics, anticoagulants","contraindication_type": "drug_class","severity": "relative","reason": "Potentiated bleeding."}]},{"generic_name": "verapamil (oral route)","contraindications": [{"contraindication_name": "severe left ventricular dysfunction","contraindication_type": "disease","severity": "absolute","reason": "Negative inotrope can worsen heart failure."},{"contraindication_name": "cardiogenic shock","contraindication_type": "disease","severity": "absolute","reason": "Further myocardial depression."},{"contraindication_name": "hypotension (SBP <90 mmHg)","contraindication_type": "disease","severity": "absolute","reason": "Vasodilation causing collapse."},{"contraindication_name": "sick sinus syndrome (no pacemaker)","contraindication_type": "disease","severity": "absolute","reason": "Severe bradycardia/asystole."},{"contraindication_name": "second- or third-degree AV block (no pacemaker)","contraindication_type": "disease","severity": "absolute","reason": "Risk of complete heart block."},{"contraindication_name": "atrial flutter/fibrillation with WPW or accessory pathway","contraindication_type": "disease","severity": "absolute","reason": "May accelerate ventricular response to ventricular fibrillation."},{"contraindication_name": "hypersensitivity to verapamil","contraindication_type": "allergy_type","severity": "absolute","reason": "Allergic reactions."},{"contraindication_name": "severe hepatic impairment","contraindication_type": "disease","severity": "relative","reason": "Impaired metabolism; use reduced dose."},{"contraindication_name": "concomitant oral beta-blockers","contraindication_type": "drug_class","severity": "relative","reason": "Additive negative inotropy and bradycardia, especially in unrecognized LV dysfunction."},{"contraindication_name": "pregnancy (Category C)","contraindication_type": "physiological_condition","severity": "relative","reason": "Only if benefit outweighs risk."}]},{"generic_name": "isosorbide dinitrate (oral route, sublingual route)","contraindications": [{"contraindication_name": "concomitant PDE5 inhibitors","contraindication_type": "drug_class","severity": "absolute","reason": "Severe hypotension and cardiovascular collapse."},{"contraindication_name": "concomitant riociguat","contraindication_type": "drug_class","severity": "absolute","reason": "Profound hypotension."},{"contraindication_name": "severe anemia","contraindication_type": "disease","severity": "absolute","reason": "Methemoglobinemia risk, decreased oxygen delivery."},{"contraindication_name": "increased intracranial pressure/cerebral hemorrhage","contraindication_type": "disease","severity": "absolute","reason": "Intracranial pressure elevation."},{"contraindication_name": "severe hypotension (SBP <90 mmHg)","contraindication_type": "disease","severity": "absolute","reason": "Vasodilation may cause cardiovascular collapse."},{"contraindication_name": "hypersensitivity to organic nitrates","contraindication_type": "allergy_type","severity": "absolute","reason": "Allergic reaction."},{"contraindication_name": "angle-closure glaucoma","contraindication_type": "disease","severity": "relative","reason": "May increase intraocular pressure."},{"contraindication_name": "hypertrophic obstructive cardiomyopathy","contraindication_type": "disease","severity": "relative","reason": "Worsening outflow obstruction."},{"contraindication_name": "pregnancy (Category C)","contraindication_type": "physiological_condition","severity": "relative","reason": "Risk-benefit evaluation necessary."}]},{"generic_name": "nitroglycerin","contraindications": [{"contraindication_name": "concomitant PDE5 inhibitors","contraindication_type": "drug_class","severity": "absolute","reason": "Life-threatening hypotension."},{"contraindication_name": "concomitant riociguat","contraindication_type": "drug_class","severity": "absolute","reason": "Profound hypotension."},{"contraindication_name": "severe anemia","contraindication_type": "disease","severity": "absolute","reason": "Methemoglobinemia risk."},{"contraindication_name": "increased intracranial pressure/cerebral hemorrhage","contraindication_type": "disease","severity": "absolute","reason": "Vasodilation increases ICP."},{"contraindication_name": "severe hypotension (SBP <90 mmHg)","contraindication_type": "disease","severity": "absolute","reason": "Cardiovascular collapse."},{"contraindication_name": "hypersensitivity to nitrates","contraindication_type": "allergy_type","severity": "absolute","reason": "Anaphylaxis."},{"contraindication_name": "angle-closure glaucoma","contraindication_type": "disease","severity": "relative","reason": "Increased intraocular pressure."},{"contraindication_name": "pregnancy (Category C)","contraindication_type": "physiological_condition","severity": "relative","reason": "Use only when benefit outweighs risk."}]},{"generic_name": "ranolazine (oral route)","contraindications": [{"contraindication_name": "severe hepatic impairment (Child-Pugh C)","contraindication_type": "disease","severity": "absolute","reason": "Reduced clearance, risk of toxicity."},{"contraindication_name": "concomitant strong CYP3A inhibitors (e.g., ketoconazole, clarithromycin)","contraindication_type": "drug_class","severity": "absolute","reason": "Substantially elevated ranolazine levels, QT prolongation, torsades de pointes."},{"contraindication_name": "hypersensitivity to ranolazine","contraindication_type": "allergy_type","severity": "absolute","reason": "Allergic reactions."},{"contraindication_name": "baseline QT interval prolongation or congenital long QT syndrome","contraindication_type": "disease","severity": "absolute","reason": "QT-prolonging effect may cause torsades de pointes."},{"contraindication_name": "severe renal impairment (CrCl <30 mL/min)","contraindication_type": "disease","severity": "relative","reason": "Increased exposure; use caution and reduce dose."},{"contraindication_name": "concomitant class Ia or III antiarrhythmics (e.g., quinidine, dofetilide, sotalol)","contraindication_type": "drug_class","severity": "relative","reason": "Additive QT prolongation."},{"contraindication_name": "pregnancy (Category C)","contraindication_type": "physiological_condition","severity": "relative","reason": "Only if benefit clearly outweighs fetal risk."}]},{"generic_name": "lorazepam (oral)","contraindications": [{"contraindication_name": "hypersensitivity to benzodiazepines","contraindication_type": "allergy_type","severity": "absolute","reason": "Anaphylaxis, angioedema."},{"contraindication_name": "acute narrow-angle glaucoma","contraindication_type": "disease","severity": "absolute","reason": "May precipitate intraocular pressure rise and acute attack."},{"contraindication_name": "severe respiratory insufficiency","contraindication_type": "disease","severity": "relative","reason": "CNS depression and respiratory depression risk."},{"contraindication_name": "sleep apnea syndrome","contraindication_type": "disease","severity": "relative","reason": "Respiratory depressant effect may worsen apnea."},{"contraindication_name": "myasthenia gravis","contraindication_type": "disease","severity": "relative","reason": "Muscle relaxant effect can exacerbate weakness."},{"contraindication_name": "severe hepatic impairment","contraindication_type": "disease","severity": "relative","reason": "Reduced glucuronidation leading to prolonged sedation."},{"contraindication_name": "pregnancy (Category D)","contraindication_type": "physiological_condition","severity": "relative","reason": "Increased risk of congenital malformations, neonatal withdrawal syndrome; use only if life-threatening indication."},{"contraindication_name": "lactation","contraindication_type": "physiological_condition","severity": "relative","reason": "Excreted in breast milk, infant sedation."},{"contraindication_name": "concomitant CNS depressants (opioids, alcohol)","contraindication_type": "drug_class","severity": "relative","reason": "Profound sedation, respiratory depression."}]},{"generic_name": "diazepam (oral)","contraindications": [{"contraindication_name": "hypersensitivity to benzodiazepines","contraindication_type": "allergy_type","severity": "absolute","reason": "Anaphylaxis."},{"contraindication_name": "acute narrow-angle glaucoma","contraindication_type": "disease","severity": "absolute","reason": "Elevated intraocular pressure."},{"contraindication_name": "severe respiratory insufficiency","contraindication_type": "disease","severity": "relative","reason": "Respiratory depression."},{"contraindication_name": "sleep apnea","contraindication_type": "disease","severity": "relative","reason": "Worsening apnea-hypopnea."},{"contraindication_name": "myasthenia gravis","contraindication_type": "disease","severity": "relative","reason": "Muscle relaxation effect."},{"contraindication_name": "severe hepatic impairment","contraindication_type": "disease","severity": "relative","reason": "Impaired metabolism; prolonged effect."},{"contraindication_name": "pregnancy (Category D)","contraindication_type": "physiological_condition","severity": "relative","reason": "Fetal harm; avoid unless critical."},{"contraindication_name": "lactation","contraindication_type": "physiological_condition","severity": "relative","reason": "Sedation in infant."},{"contraindication_name": "concomitant CNS depressants","contraindication_type": "drug_class","severity": "relative","reason": "Additive sedation and respiratory depression."}]},{"generic_name": "Alprazolam Oral Solution","contraindications": [{"contraindication_name": "concomitant strong CYP3A inhibitors (e.g., itraconazole, ketoconazole)","contraindication_type": "drug_class","severity": "absolute","reason": "Markedly elevated alprazolam levels; oversedation, respiratory depression."},{"contraindication_name": "acute narrow-angle glaucoma","contraindication_type": "disease","severity": "absolute","reason": "May provoke acute attack."},{"contraindication_name": "hypersensitivity to benzodiazepines","contraindication_type": "allergy_type","severity": "absolute","reason": "Anaphylaxis."},{"contraindication_name": "severe respiratory insufficiency","contraindication_type": "disease","severity": "relative","reason": "Respiratory depression."},{"contraindication_name": "myasthenia gravis","contraindication_type": "disease","severity": "relative","reason": "Muscle relaxant properties."},{"contraindication_name": "severe hepatic impairment","contraindication_type": "disease","severity": "relative","reason": "Decreased clearance, prolonged sedation."},{"contraindication_name": "pregnancy (Category D)","contraindication_type": "physiological_condition","severity": "relative","reason": "Teratogenic risk, neonatal withdrawal; use only when essential."},{"contraindication_name": "lactation","contraindication_type": "physiological_condition","severity": "relative","reason": "Possible infant sedation."},{"contraindication_name": "concomitant CNS depressants","contraindication_type": "drug_class","severity": "relative","reason": "Additive sedation."}]},{"generic_name": "risperidone (oral)","contraindications": [{"contraindication_name": "hypersensitivity to risperidone or paliperidone","contraindication_type": "allergy_type","severity": "absolute","reason": "Anaphylaxis, angioedema."},{"contraindication_name": "dementia-related psychosis in elderly patients","contraindication_type": "disease","severity": "relative","reason": "Increased risk of cerebrovascular events and mortality (Black Box Warning)."},{"contraindication_name": "Parkinson disease","contraindication_type": "disease","severity": "relative","reason": "Dopamine blockade may exacerbate motor symptoms."},{"contraindication_name": "dehydration or hypovolemia","contraindication_type": "disease","severity": "relative","reason": "Orthostatic hypotension and syncope risk."},{"contraindication_name": "long QT syndrome or history of cardiac arrhythmias","contraindication_type": "disease","severity": "relative","reason": "QT prolongation potential; avoid with other QT prolonging drugs."},{"contraindication_name": "seizure disorders","contraindication_type": "disease","severity": "relative","reason": "Lowers seizure threshold."},{"contraindication_name": "severe renal or hepatic impairment","contraindication_type": "disease","severity": "relative","reason": "Dose adjustment required; increased sensitivity."},{"contraindication_name": "pregnancy (Category C)","contraindication_type": "physiological_condition","severity": "relative","reason": "Neonatal extrapyramidal symptoms, withdrawal; use only if benefit outweighs risk."},{"contraindication_name": "concomitant dopamine agonists (levodopa)","contraindication_type": "drug_class","severity": "relative","reason": "Antagonism of antiparkinsonian effect."}]},{"generic_name": "clorazepate (oral route)","contraindications": [{"contraindication_name": "acute narrow-angle glaucoma","contraindication_type": "disease","severity": "absolute","reason": "Increased intraocular pressure."},{"contraindication_name": "hypersensitivity to benzodiazepines","contraindication_type": "allergy_type","severity": "absolute","reason": "Anaphylaxis."},{"contraindication_name": "severe respiratory insufficiency","contraindication_type": "disease","severity": "relative","reason": "Respiratory depression."},{"contraindication_name": "myasthenia gravis","contraindication_type": "disease","severity": "relative","reason": "Muscle relaxation."},{"contraindication_name": "severe hepatic impairment","contraindication_type": "disease","severity": "relative","reason": "Altered metabolism, prolonged effect."},{"contraindication_name": "pregnancy (Category D)","contraindication_type": "physiological_condition","severity": "relative","reason": "Congenital malformation risk, neonatal withdrawal; restrict use."},{"contraindication_name": "lactation","contraindication_type": "physiological_condition","severity": "relative","reason": "Infant sedation."},{"contraindication_name": "concomitant CNS depressants","contraindication_type": "drug_class","severity": "relative","reason": "Additive sedation."}]},{"generic_name": "doxepin (capsules, oral concentrate)","contraindications": [{"contraindication_name": "concomitant MAO inhibitors or within 14 days of discontinuation","contraindication_type": "drug_class","severity": "absolute","reason": "Serotonin syndrome, hyperpyretic crisis, convulsions, death."},{"contraindication_name": "acute recovery phase of myocardial infarction","contraindication_type": "disease","severity": "absolute","reason": "Cardiotoxic effects of TCAs can cause arrhythmias."},{"contraindication_name": "hypersensitivity to doxepin or other TCAs","contraindication_type": "allergy_type","severity": "absolute","reason": "Anaphylaxis."},{"contraindication_name": "urinary retention (e.g., BPH)","contraindication_type": "disease","severity": "relative","reason": "Potent anticholinergic effects worsen retention."},{"contraindication_name": "untreated narrow-angle glaucoma","contraindication_type": "disease","severity": "absolute","reason": "Anticholinergic action precipitates acute attack."},{"contraindication_name": "severe hepatic impairment","contraindication_type": "disease","severity": "relative","reason": "Impaired metabolism, increased toxicity."},{"contraindication_name": "pregnancy","contraindication_type": "physiological_condition","severity": "relative","reason": "Neonatal withdrawal symptoms; use only if clearly needed."},{"contraindication_name": "concomitant CNS depressants (alcohol, benzodiazepines)","contraindication_type": "drug_class","severity": "relative","reason": "Additive sedation and respiratory depression."}]},{"generic_name": "amitriptyline and perphenazine","contraindications": [{"contraindication_name": "concomitant MAO inhibitors or within 14 days","contraindication_type": "drug_class","severity": "absolute","reason": "Amitriptyline interaction: serotonin syndrome, hypertensive crisis."},{"contraindication_name": "acute myocardial infarction recovery phase","contraindication_type": "disease","severity": "absolute","reason": "Amitriptyline cardiotoxicity."},{"contraindication_name": "hypersensitivity to amitriptyline, perphenazine, or phenothiazines","contraindication_type": "allergy_type","severity": "absolute","reason": "Anaphylaxis, cross-reactivity."},{"contraindication_name": "untreated narrow-angle glaucoma","contraindication_type": "disease","severity": "absolute","reason": "Anticholinergic effect of amitriptyline and perphenazine."},{"contraindication_name": "urinary retention","contraindication_type": "disease","severity": "relative","reason": "Anticholinergic action of both drugs."},{"contraindication_name": "dementia-related psychosis in elderly","contraindication_type": "disease","severity": "relative","reason": "Perphenazine increases mortality risk (Black Box)."},{"contraindication_name": "seizure disorders","contraindication_type": "disease","severity": "relative","reason": "Both components lower seizure threshold."},{"contraindication_name": "pregnancy","contraindication_type": "physiological_condition","severity": "relative","reason": "Both drugs are Pregnancy Category D; risk of teratogenicity and neonatal withdrawal."},{"contraindication_name": "concomitant CNS depressants","contraindication_type": "drug_class","severity": "relative","reason": "Profound sedation."}]},{"generic_name": "diazepam (oral route)","contraindications": [{"contraindication_name": "hypersensitivity to benzodiazepines","contraindication_type": "allergy_type","severity": "absolute","reason": "Anaphylaxis."},{"contraindication_name": "acute narrow-angle glaucoma","contraindication_type": "disease","severity": "absolute","reason": "Increased intraocular pressure."},{"contraindication_name": "severe respiratory insufficiency","contraindication_type": "disease","severity": "relative","reason": "Respiratory depression."},{"contraindication_name": "myasthenia gravis","contraindication_type": "disease","severity": "relative","reason": "Muscle relaxant effect."},{"contraindication_name": "severe hepatic impairment","contraindication_type": "disease","severity": "relative","reason": "Impaired clearance."},{"contraindication_name": "pregnancy (Category D)","contraindication_type": "physiological_condition","severity": "relative","reason": "Fetal risk; use only if essential."},{"contraindication_name": "lactation","contraindication_type": "physiological_condition","severity": "relative","reason": "Infant sedation."},{"contraindication_name": "concomitant CNS depressants","contraindication_type": "drug_class","severity": "relative","reason": "Additive depression."}]},{"generic_name": "phenytoin (oral)","contraindications": [{"contraindication_name": "hypersensitivity to phenytoin or hydantoins","contraindication_type": "allergy_type","severity": "absolute","reason": "Stevens-Johnson syndrome, DRESS."},{"contraindication_name": "sinus bradycardia, sinoatrial block, second- or third-degree AV block","contraindication_type": "disease","severity": "absolute","reason": "Phenytoin has cardiac depressant effects, risk of asystole."},{"contraindication_name": "acute intermittent porphyria","contraindication_type": "disease","severity": "absolute","reason": "Phenytoin induces ALA synthase and can precipitate an acute attack."},{"contraindication_name": "pregnancy (Category D)","contraindication_type": "physiological_condition","severity": "relative","reason": "Fetal hydantoin syndrome; use only if seizure control outweighs risk."},{"contraindication_name": "severe hepatic impairment","contraindication_type": "disease","severity": "relative","reason": "Reduced metabolism and high protein binding changes; monitor levels."},{"contraindication_name": "concomitant delavirdine or other non-nucleoside reverse transcriptase inhibitors","contraindication_type": "drug_class","severity": "relative","reason": "Phenytoin reduces their concentrations, risking viral resistance."},{"contraindication_name": "concomitant substrates of CYP3A4/2C9 with narrow therapeutic index (e.g., warfarin)","contraindication_type": "drug_class","severity": "relative","reason": "Induction/inhibition leading to loss of efficacy or toxicity."}]},{"generic_name": "prochlorperazine (oral/injection)","contraindications": [{"contraindication_name": "hypersensitivity to prochlorperazine or other phenothiazines","contraindication_type": "allergy_type","severity": "absolute","reason": "Anaphylaxis, cross-sensitivity."},{"contraindication_name": "coma or severe CNS depression","contraindication_type": "disease","severity": "absolute","reason": "Can further depress consciousness."},{"contraindication_name": "bone marrow suppression","contraindication_type": "disease","severity": "absolute","reason": "Risk of agranulocytosis, leukopenia."},{"contraindication_name": "pediatric patients <2 years","contraindication_type": "physiological_condition","severity": "absolute","reason": "High risk of extrapyramidal symptoms and respiratory depression."},{"contraindication_name": "untreated narrow-angle glaucoma","contraindication_type": "disease","severity": "relative","reason": "Anticholinergic effect raises intraocular pressure."},{"contraindication_name": "prostatic hyperplasia with urinary retention","contraindication_type": "disease","severity": "relative","reason": "Anticholinergic action."},{"contraindication_name": "seizure disorders","contraindication_type": "disease","severity": "relative","reason": "Lowers seizure threshold."},{"contraindication_name": "pregnancy","contraindication_type": "physiological_condition","severity": "relative","reason": "Possible neonatal extrapyramidal effects; use only if needed."},{"contraindication_name": "concomitant drugs that prolong QT interval","contraindication_type": "drug_class","severity": "relative","reason": "Additive risk of torsades de pointes."}]},{"generic_name": "amitriptyline and chlordiazepoxide","contraindications": [{"contraindication_name": "concomitant MAO inhibitors or within 14 days","contraindication_type": "drug_class","severity": "absolute","reason": "Amitriptyline interaction: serotonin syndrome, hypertensive crisis."},{"contraindication_name": "acute myocardial infarction recovery","contraindication_type": "disease","severity": "absolute","reason": "Amitriptyline cardiotoxicity."},{"contraindication_name": "hypersensitivity to amitriptyline or benzodiazepines","contraindication_type": "allergy_type","severity": "absolute","reason": "Anaphylaxis."},{"contraindication_name": "untreated narrow-angle glaucoma","contraindication_type": "disease","severity": "absolute","reason": "Anticholinergic effect of amitriptyline; chlordiazepoxide may also raise IOP."},{"contraindication_name": "urinary retention","contraindication_type": "disease","severity": "relative","reason": "Amitriptyline anticholinergic effect."},{"contraindication_name": "severe respiratory insufficiency","contraindication_type": "disease","severity": "relative","reason": "Chlordiazepoxide can cause respiratory depression."},{"contraindication_name": "pregnancy","contraindication_type": "physiological_condition","severity": "relative","reason": "Both drugs are Category D; neonatal withdrawal syndrome, teratogenicity."},{"contraindication_name": "concomitant CNS depressants","contraindication_type": "drug_class","severity": "relative","reason": "Additive sedation."}]},{"generic_name": "prochlorperazine (rectal)","contraindications": [{"contraindication_name": "hypersensitivity to prochlorperazine or phenothiazines","contraindication_type": "allergy_type","severity": "absolute","reason": "Anaphylaxis."},{"contraindication_name": "coma or severe CNS depression","contraindication_type": "disease","severity": "absolute","reason": "Further CNS depression."},{"contraindication_name": "bone marrow suppression","contraindication_type": "disease","severity": "absolute","reason": "Agranulocytosis risk."},{"contraindication_name": "pediatric patients <2 years","contraindication_type": "physiological_condition","severity": "absolute","reason": "Extrapyramidal side effects and respiratory depression."},{"contraindication_name": "untreated narrow-angle glaucoma","contraindication_type": "disease","severity": "relative","reason": "Anticholinergic effect."},{"contraindication_name": "urinary retention (BPH)","contraindication_type": "disease","severity": "relative","reason": "Anticholinergic effect."},{"contraindication_name": "pregnancy","contraindication_type": "physiological_condition","severity": "relative","reason": "Neonatal extrapyramidal syndrome; restrict use."}]},{"generic_name": "meprobamate","contraindications": [{"contraindication_name": "hypersensitivity to meprobamate or carisoprodol","contraindication_type": "allergy_type","severity": "absolute","reason": "Cross-sensitivity; anaphylaxis."},{"contraindication_name": "acute intermittent porphyria","contraindication_type": "disease","severity": "absolute","reason": "May precipitate a porphyric attack."},{"contraindication_name": "severe renal impairment","contraindication_type": "disease","severity": "relative","reason": "Reduced clearance, accumulation, excessive sedation."},{"contraindication_name": "severe hepatic impairment","contraindication_type": "disease","severity": "relative","reason": "Impaired metabolism."},{"contraindication_name": "pregnancy","contraindication_type": "physiological_condition","severity": "relative","reason": "Possible congenital malformations; avoid if possible."},{"contraindication_name": "history of substance use disorder","contraindication_type": "disease","severity": "relative","reason": "Abuse potential."},{"contraindication_name": "concomitant CNS depressants","contraindication_type": "drug_class","severity": "relative","reason": "Additive sedation."}]},{"generic_name": "fluticasone, umeclidinium, and vilanterol","contraindications": [{"contraindication_name": "hypersensitivity to any component","contraindication_type": "allergy_type","severity": "absolute","reason": "Anaphylaxis."},{"contraindication_name": "severe milk protein allergy","contraindication_type": "allergy_type","severity": "absolute","reason": "Product contains lactose which may contain trace milk protein."},{"contraindication_name": "uncontrolled narrow-angle glaucoma","contraindication_type": "disease","severity": "relative","reason": "Umeclidinium (anticholinergic) may increase intraocular pressure."},{"contraindication_name": "urinary retention (BPH or bladder neck obstruction)","contraindication_type": "disease","severity": "relative","reason": "Anticholinergic effect of umeclidinium."},{"contraindication_name": "severe cardiovascular disease (arrhythmias, ischemic heart disease)","contraindication_type": "disease","severity": "relative","reason": "Vilanterol (LABA) can cause tachycardia and myocardial ischemia."},{"contraindication_name": "acute bronchospasm (as sole therapy)","contraindication_type": "disease","severity": "relative","reason": "Not a rescue medication; LABAs need a SABA for acute episodes."},{"contraindication_name": "pregnancy","contraindication_type": "physiological_condition","severity": "relative","reason": "Limited data; use only if benefit outweighs risk."}]},{"generic_name": "benralizumab","contraindications": [{"contraindication_name": "hypersensitivity to benralizumab or excipients","contraindication_type": "allergy_type","severity": "absolute","reason": "Anaphylaxis; post-injection systemic reactions reported."},{"contraindication_name": "pre-existing helminth infection","contraindication_type": "disease","severity": "relative","reason": "Eosinophils participate in parasite clearance; treat infection prior to therapy."},{"contraindication_name": "pregnancy","contraindication_type": "physiological_condition","severity": "relative","reason": "Insufficient human data; use only if clearly needed."}]},{"generic_name": "mepolizumab","contraindications": [{"contraindication_name": "hypersensitivity to mepolizumab or excipients","contraindication_type": "allergy_type","severity": "absolute","reason": "Anaphylaxis risk."},{"contraindication_name": "pre-existing helminth infection","contraindication_type": "disease","severity": "relative","reason": "Treat parasitic infection before initiating."},{"contraindication_name": "pregnancy","contraindication_type": "physiological_condition","severity": "relative","reason": "Limited data; use only if necessary."}]},{"generic_name": "benralizumab Brand name: Fasenra","contraindications": [{"contraindication_name": "hypersensitivity to benralizumab","contraindication_type": "allergy_type","severity": "absolute","reason": "Anaphylaxis."},{"contraindication_name": "helminth infection","contraindication_type": "disease","severity": "relative","reason": "Pre-existing parasite infestation should be treated."},{"contraindication_name": "pregnancy","contraindication_type": "physiological_condition","severity": "relative","reason": "Uncertain fetal safety."}]},{"generic_name": "tezepelumab","contraindications": [{"contraindication_name": "hypersensitivity to tezepelumab or excipients","contraindication_type": "allergy_type","severity": "absolute","reason": "Anaphylaxis."},{"contraindication_name": "pre-existing helminth infection","contraindication_type": "disease","severity": "relative","reason": "May reduce eosinophils needed for parasite defense."},{"contraindication_name": "pregnancy","contraindication_type": "physiological_condition","severity": "relative","reason": "No adequate human data; use only if clearly required."}]},{"generic_name": "tezepelumab-ekko","contraindications": [{"contraindication_name": "hypersensitivity to tezepelumab-ekko","contraindication_type": "allergy_type","severity": "absolute","reason": "Anaphylaxis."},{"contraindication_name": "helminth infection","contraindication_type": "disease","severity": "relative","reason": "Interference with parasite clearance."},{"contraindication_name": "pregnancy","contraindication_type": "physiological_condition","severity": "relative","reason": "Limited pregnancy data."}]},{"generic_name": "formoterol and mometasone","contraindications": [{"contraindication_name": "hypersensitivity to any component","contraindication_type": "allergy_type","severity": "absolute","reason": "Anaphylaxis."},{"contraindication_name": "severe milk protein allergy (if lactose-containing formulation)","contraindication_type": "allergy_type","severity": "absolute","reason": "Possible trace milk protein triggering reactions."},{"contraindication_name": "asthma exacerbation or acute bronchospasm (as sole therapy)","contraindication_type": "disease","severity": "relative","reason": "Formoterol is not a rescue medication."},{"contraindication_name": "active untreated tuberculosis or systemic fungal/viral infections","contraindication_type": "disease","severity": "relative","reason": "Corticosteroid immunosuppression may exacerbate."},{"contraindication_name": "severe cardiovascular disease (arrhythmia, hypertension)","contraindication_type": "disease","severity": "relative","reason": "Formoterol can cause tachycardia and increased BP."},{"contraindication_name": "pregnancy (Category C)","contraindication_type": "physiological_condition","severity": "relative","reason": "Use if benefit justifies fetal risk."}]},{"generic_name": "ipratropium (inhalation route)","contraindications": [{"contraindication_name": "hypersensitivity to ipratropium, atropine, or derivatives","contraindication_type": "allergy_type","severity": "absolute","reason": "Anaphylaxis, bronchospasm."},{"contraindication_name": "hypersensitivity to soya lecithin or related food allergens","contraindication_type": "allergy_type","severity": "absolute","reason": "Some formulations contain soya lecithin."},{"contraindication_name": "narrow-angle glaucoma","contraindication_type": "disease","severity": "relative","reason": "May increase intraocular pressure, especially with nebulizer facial contact."},{"contraindication_name": "bladder neck obstruction / prostatic hyperplasia","contraindication_type": "disease","severity": "relative","reason": "Anticholinergic effect may precipitate urinary retention."}]},{"generic_name": "fluticasone and vilanterol","contraindications": [{"contraindication_name": "hypersensitivity to components or milk protein (if lactose carrier)","contraindication_type": "allergy_type","severity": "absolute","reason": "Anaphylaxis."},{"contraindication_name": "acute bronchospasm or status asthmaticus (as monotherapy)","contraindication_type": "disease","severity": "relative","reason": "Vilanterol is a LABA, not a rescue drug."},{"contraindication_name": "untreated systemic infections (tuberculosis, fungal)","contraindication_type": "disease","severity": "relative","reason": "Fluticasone immunosuppression."},{"contraindication_name": "severe cardiovascular disease","contraindication_type": "disease","severity": "relative","reason": "Vilanterol may exacerbate arrhythmias."},{"contraindication_name": "pregnancy (Category C)","contraindication_type": "physiological_condition","severity": "relative","reason": "Benefit-risk assessment required."}]},{"generic_name": "ipratropium inhalation","contraindications": [{"contraindication_name": "hypersensitivity to ipratropium or atropine","contraindication_type": "allergy_type","severity": "absolute","reason": "Anaphylaxis."},{"contraindication_name": "soy allergy (if product contains soya lecithin)","contraindication_type": "allergy_type","severity": "absolute","reason": "Cross-reactivity."},{"contraindication_name": "angle-closure glaucoma","contraindication_type": "disease","severity": "relative","reason": "Intraocular pressure rise."},{"contraindication_name": "prostatic hyperplasia / bladder neck obstruction","contraindication_type": "disease","severity": "relative","reason": "Urinary retention."}]},{"generic_name": "methylprednisolone (oral)","contraindications": [{"contraindication_name": "systemic fungal infections","contraindication_type": "disease","severity": "absolute","reason": "Corticosteroid immunosuppression can worsen and mask infection."},{"contraindication_name": "hypersensitivity to methylprednisolone or components","contraindication_type": "allergy_type","severity": "absolute","reason": "Anaphylaxis."},{"contraindication_name": "live or live-attenuated vaccines","contraindication_type": "drug_class","severity": "relative","reason": "Immunosuppression increases risk of disseminated infection."},{"contraindication_name": "active peptic ulcer disease","contraindication_type": "disease","severity": "relative","reason": "Increased risk of perforation and bleeding."},{"contraindication_name": "uncontrolled diabetes mellitus","contraindication_type": "disease","severity": "relative","reason": "Hyperglycemic effect."},{"contraindication_name": "severe osteoporosis","contraindication_type": "disease","severity": "relative","reason": "Accelerated bone loss."},{"contraindication_name": "pregnancy (Category C)","contraindication_type": "physiological_condition","severity": "relative","reason": "Cleft palate risk in first trimester; use when benefit outweighs risk."},{"contraindication_name": "concomitant NSAIDs","contraindication_type": "drug_class","severity": "relative","reason": "Additive gastrointestinal ulceration risk."}]},{"generic_name": "dexamethasone (oral)","contraindications": [{"contraindication_name": "systemic fungal infections","contraindication_type": "disease","severity": "absolute","reason": "Immunosuppression can be fatal."},{"contraindication_name": "hypersensitivity to dexamethasone","contraindication_type": "allergy_type","severity": "absolute","reason": "Anaphylaxis."},{"contraindication_name": "live vaccines","contraindication_type": "drug_class","severity": "relative","reason": "Risk of disseminated infection."},{"contraindication_name": "active gastrointestinal ulcer","contraindication_type": "disease","severity": "relative","reason": "Bleeding/perforation."},{"contraindication_name": "uncontrolled diabetes","contraindication_type": "disease","severity": "relative","reason": "Hyperglycemia."},{"contraindication_name": "severe psychiatric disorders","contraindication_type": "disease","severity": "relative","reason": "Corticosteroids can cause psychosis or mood destabilization."},{"contraindication_name": "pregnancy (Category C)","contraindication_type": "physiological_condition","severity": "relative","reason": "Teratogenicity possible; use for fetal lung maturity may be justified."}]},{"generic_name": "ciclesonide (inhalation)","contraindications": [{"contraindication_name": "hypersensitivity to ciclesonide or excipients","contraindication_type": "allergy_type","severity": "absolute","reason": "Immediate hypersensitivity."},{"contraindication_name": "severe milk protein allergy (if lactose carrier)","contraindication_type": "allergy_type","severity": "absolute","reason": "Trace milk protein may cause reaction."},{"contraindication_name": "asthma exacerbation or acute bronchospasm","contraindication_type": "disease","severity": "relative","reason": "Not a rescue medication."},{"contraindication_name": "active pulmonary tuberculosis or untreated fungal/viral infection","contraindication_type": "disease","severity": "relative","reason": "Local immunosuppression may mask or worsen."},{"contraindication_name": "pregnancy (Category C)","contraindication_type": "physiological_condition","severity": "relative","reason": "Benefit-risk decision."}]},{"generic_name": "levalbuterol inhalation","contraindications": [{"contraindication_name": "hypersensitivity to levalbuterol or albuterol","contraindication_type": "allergy_type","severity": "absolute","reason": "Anaphylaxis."},{"contraindication_name": "severe cardiovascular disease (arrhythmia, coronary artery disease)","contraindication_type": "disease","severity": "relative","reason": "Beta-agonism can cause tachycardia, provoke ischemia."},{"contraindication_name": "hyperthyroidism","contraindication_type": "disease","severity": "relative","reason": "Excessive cardiovascular stimulation."},{"contraindication_name": "diabetes mellitus","contraindication_type": "disease","severity": "relative","reason": "Risk of hyperglycemia and ketoacidosis."},{"contraindication_name": "seizure disorders","contraindication_type": "disease","severity": "relative","reason": "CNS stimulation may lower threshold."},{"contraindication_name": "pregnancy (Category C)","contraindication_type": "physiological_condition","severity": "relative","reason": "May inhibit uterine contractions; use only if benefit outweighs risk."},{"contraindication_name": "concomitant non-potassium-sparing diuretics","contraindication_type": "drug_class","severity": "relative","reason": "Exacerbated hypokalemia."}]},{"generic_name": "Ipratropium Inhalation Solution","contraindications": [{"contraindication_name": "hypersensitivity to ipratropium, atropine, or soya lecithin","contraindication_type": "allergy_type","severity": "absolute","reason": "Anaphylaxis."},{"contraindication_name": "narrow-angle glaucoma","contraindication_type": "disease","severity": "relative","reason": "Increased intraocular pressure."},{"contraindication_name": "bladder neck obstruction / BPH","contraindication_type": "disease","severity": "relative","reason": "Urinary retention."}]},{"generic_name": "triamcinolone (oral)","contraindications": [{"contraindication_name": "systemic fungal infections","contraindication_type": "disease","severity": "absolute","reason": "Immunosuppression may be fatal."},{"contraindication_name": "hypersensitivity to triamcinolone","contraindication_type": "allergy_type","severity": "absolute","reason": "Anaphylaxis."},{"contraindication_name": "live vaccines","contraindication_type": "drug_class","severity": "relative","reason": "Disseminated infection risk."},{"contraindication_name": "active peptic ulcer","contraindication_type": "disease","severity": "relative","reason": "GI perforation and bleeding."},{"contraindication_name": "uncontrolled diabetes","contraindication_type": "disease","severity": "relative","reason": "Hyperglycemia."},{"contraindication_name": "osteoporosis","contraindication_type": "disease","severity": "relative","reason": "Bone loss."},{"contraindication_name": "pregnancy (Category C)","contraindication_type": "physiological_condition","severity": "relative","reason": "Potential fetal harm; use if benefit justifies."}]},{"generic_name": "dexamethasone (oral route)","contraindications": [{"contraindication_name": "systemic fungal infections","contraindication_type": "disease","severity": "absolute","reason": "Life-threatening immunosuppression."},{"contraindication_name": "hypersensitivity to dexamethasone","contraindication_type": "allergy_type","severity": "absolute","reason": "Anaphylaxis."},{"contraindication_name": "live vaccines","contraindication_type": "drug_class","severity": "relative","reason": "Risk of disseminated disease."},{"contraindication_name": "active GI ulcer","contraindication_type": "disease","severity": "relative","reason": "Perforation/bleeding."},{"contraindication_name": "uncontrolled diabetes / psychosis","contraindication_type": "disease","severity": "relative","reason": "Hyperglycemia and mood destabilization."},{"contraindication_name": "pregnancy (Category C)","contraindication_type": "physiological_condition","severity": "relative","reason": "Teratogenicity risk; may be used for premature labor lung maturation."}]},{"generic_name": "triamcinolone (injection)","contraindications": [{"contraindication_name": "systemic fungal infections","contraindication_type": "disease","severity": "absolute","reason": "Immunosuppression risk."},{"contraindication_name": "hypersensitivity to triamcinolone or components","contraindication_type": "allergy_type","severity": "absolute","reason": "Anaphylaxis."},{"contraindication_name": "active infection at injection site","contraindication_type": "disease","severity": "absolute","reason": "Intra-articular or soft tissue injection can exacerbate infection."},{"contraindication_name": "idiopathic thrombocytopenic purpura (for intramuscular injection)","contraindication_type": "disease","severity": "absolute","reason": "Risk of intramuscular hematoma."},{"contraindication_name": "live vaccines","contraindication_type": "drug_class","severity": "relative","reason": "Possible impaired vaccine response and infection."},{"contraindication_name": "pregnancy (Category C)","contraindication_type": "physiological_condition","severity": "relative","reason": "Use only if clearly needed."}]},{"generic_name": "methylprednisolone (injection)","contraindications": [{"contraindication_name": "systemic fungal infections","contraindication_type": "disease","severity": "absolute","reason": "Fatal immunosuppression."},{"contraindication_name": "hypersensitivity to methylprednisolone or components","contraindication_type": "allergy_type","severity": "absolute","reason": "Anaphylaxis."},{"contraindication_name": "active untreated infections (sepsis, tuberculosis)","contraindication_type": "disease","severity": "relative","reason": "May mask or worsen infection."},{"contraindication_name": "live vaccines","contraindication_type": "drug_class","severity": "relative","reason": "Immunosuppression risk."},{"contraindication_name": "peptic ulcer disease","contraindication_type": "disease","severity": "relative","reason": "GI hemorrhage."},{"contraindication_name": "pregnancy (Category C)","contraindication_type": "physiological_condition","severity": "relative","reason": "Potential fetal harm."}]},{"generic_name": "Caffeine","contraindications": [{"contraindication_name": "hypersensitivity to caffeine or components","contraindication_type": "allergy_type","severity": "absolute","reason": "Anaphylaxis is rare but possible."},{"contraindication_name": "unstable cardiac arrhythmias or recent myocardial infarction","contraindication_type": "disease","severity": "relative","reason": "CNS stimulation and positive chronotropy may provoke arrhythmia."},{"contraindication_name": "severe anxiety disorder or insomnia","contraindication_type": "disease","severity": "relative","reason": "Exacerbates agitation and sleep disturbance."},{"contraindication_name": "active peptic ulcer disease","contraindication_type": "disease","severity": "relative","reason": "Stimulates gastric acid secretion; may impair healing."},{"contraindication_name": "severe hepatic impairment","contraindication_type": "disease","severity": "relative","reason": "Reduced caffeine metabolism; may cause toxicity."},{"contraindication_name": "concomitant adenosine for supraventricular tachycardia","contraindication_type": "drug_class","severity": "relative","reason": "Caffeine is an adenosine receptor antagonist; may reduce adenosine efficacy."},{"contraindication_name": "pregnancy (Category C)","contraindication_type": "physiological_condition","severity": "relative","reason": "High doses associated with spontaneous abortion and fetal growth restriction; limit intake."}]}]